MANIFEST.in
msgcodegen.py
setup.py
version.py
python3_riak_pb.egg-info/PKG-INFO
python3_riak_pb.egg-info/SOURCES.txt
python3_riak_pb.egg-info/dependency_links.txt
python3_riak_pb.egg-info/requires.txt
python3_riak_pb.egg-info/top_level.txt
python3_riak_pb.egg-info/zip-safe
riak_pb/__init__.py
riak_pb/messages.py
riak_pb/riak_dt_pb2.py
riak_pb/riak_kv_pb2.py
riak_pb/riak_pb2.py
riak_pb/riak_search_pb2.py
riak_pb/riak_ts_pb2.py
riak_pb/riak_yokozuna_pb2.py
src/riak_pb_messages.csv