Metadata-Version: 1.1
Name: python3_riak_pb
Version: 2.1.1.0
Summary: Riak Protocol Buffers Messages
Home-page: https://github.com/basho/riak_pb
Author: Basho Technologies
Author-email: clients@basho.com
License: Apache 2
Platform: Platform Independent
Classifier: License :: OSI Approved :: Apache Software License
Classifier: Intended Audience :: Developers
Classifier: Operating System :: OS Independent
Classifier: Programming Language :: Python :: 2.6
Classifier: Programming Language :: Python :: 2.7
Classifier: Programming Language :: Python :: 3.3
Classifier: Programming Language :: Python :: 3.4
Classifier: Topic :: Database
Requires: six(>=1.8.0)
Requires: python3_protobuf(>=2.4.1,<2.6.0)
